LICENSE
README.rst
setup.py
Python_EasyGraph1.egg-info/PKG-INFO
Python_EasyGraph1.egg-info/SOURCES.txt
Python_EasyGraph1.egg-info/dependency_links.txt
Python_EasyGraph1.egg-info/requires.txt
Python_EasyGraph1.egg-info/top_level.txt
easygraph/__init__.py
easygraph/classes/__init__.py
easygraph/classes/directed_graph.py
easygraph/classes/graph.py
easygraph/classes/GraphC/Graph.cpp
easygraph/classes/GraphC/GraphEdge.cpp
easygraph/classes/GraphC/GraphEdges.cpp
easygraph/classes/GraphC/GraphEdgesIter.cpp
easygraph/classes/GraphC/GraphMap.cpp
easygraph/classes/GraphC/GraphMapIter.cpp
easygraph/classes/GraphC/GraphModule.cpp
easygraph/classes/GraphC/ModuleMethods.cpp
easygraph/datasets/__init__.py
easygraph/datasets/get_sample_graph.py
easygraph/functions/__init__.py
easygraph/functions/centrality/__init__.py
easygraph/functions/centrality/betweenness.py
easygraph/functions/centrality/clossness.py
easygraph/functions/centrality/degree.py
easygraph/functions/centrality/flowbetweenness.py
easygraph/functions/community/LPA.py
easygraph/functions/community/__init__.py
easygraph/functions/community/modularity.py
easygraph/functions/community/modularity_max_detection.py
easygraph/functions/components/__init__.py
easygraph/functions/components/biconnected.py
easygraph/functions/components/connected.py
easygraph/functions/components/ego_betweenness.py
easygraph/functions/drawing/__init__.py
easygraph/functions/drawing/drawing.py
easygraph/functions/drawing/plot.py
easygraph/functions/drawing/positioning.py
easygraph/functions/graph_embedding/NOBE.py
easygraph/functions/graph_embedding/__init__.py
easygraph/functions/graph_embedding/deepwalk.py
easygraph/functions/graph_embedding/line.py
easygraph/functions/graph_embedding/node2vec.py
easygraph/functions/graph_embedding/sdne.py
easygraph/functions/graph_generator/RandomNetwork.py
easygraph/functions/graph_generator/__init__.py
easygraph/functions/not_sorted/__init__.py
easygraph/functions/not_sorted/bridges.py
easygraph/functions/not_sorted/laplacian.py
easygraph/functions/not_sorted/mst.py
easygraph/functions/not_sorted/pagerank.py
easygraph/functions/path/__init__.py
easygraph/functions/path/path.py
