Metadata-Version: 2.1
Name: Python-EasyGraph1
Version: 0.2a29
Summary: Easy Graph
Home-page: https://github.com/easy-graph/Easy-Graph
Author: Fudan MSN Group
Author-email: easygraph@163.com
License: UNKNOWN
Platform: UNKNOWN
Classifier: Programming Language :: Python :: 3.6
Classifier: Programming Language :: Python :: 3.7
Classifier: Programming Language :: Python :: 3.8
Classifier: License :: OSI Approved :: BSD License
Classifier: Operating System :: OS Independent
Requires-Python: >=3.6,<3.9
License-File: LICENSE
